{
  "mbook": "Book02",
  "msdisciplines": [
    "SixthSense",
    "Healing",
    {
      "WeaponSkill": "Sword"
    },
    "MindBlast",
    "AnimalKinship",
    "MindOverMatter"
  ],
  "variable": {
    "items": {
      "Sword": 1,
      "Shield": 1
    },
    "gold": 23,
    "flags": []
  },
  "msentries": [
    {
      "meendurance": 20,
      "mskill": 10,
      "mscore": 0.6065132862386725,
      "mratio": {
        "radix": 16,
        "value": "1d7caed212ff68889eb8c51e3c6417da0c283aea7963728350d/309e07d27ff3e9b54f2fdadc71dac97ed43e020000000000000"
      },
      "states": 6303588
    }
  ]
}