{
  "mbook": "Book02",
  "msdisciplines": [
    "Hunting",
    "Tracking",
    "Healing",
    {
      "WeaponSkill": "Sword"
    },
    "MindBlast",
    "AnimalKinship"
  ],
  "variable": {
    "items": {
      "Sword": 1,
      "Shield": 1
    },
    "gold": 27,
    "flags": []
  },
  "msentries": [
    {
      "meendurance": 20,
      "mskill": 10,
      "mscore": 0.6404206536550326,
      "mratio": {
        "radix": 16,
        "value": "18e88e5744f59179a6511e13f632af2f3c890e52de96ff6a0c3/26e4d30eccc3215dd8f3157d27e23acbdcfe680000000000000"
      },
      "states": 4615794
    }
  ]
}