{
  "mbook": "Book04",
  "msdisciplines": [
    "Hunting",
    "SixthSense",
    "Healing",
    {
      "WeaponSkill": "Sword"
    },
    "MindShield",
    "MindBlast",
    "AnimalKinship",
    "MindOverMatter"
  ],
  "variable": {
    "items": {
      "Dagger": 1,
      "Sword": 1,
      "Shield": 1,
      "BodyArmor": 1,
      "Meal": 5,
      "Laumspur": 2
    },
    "gold": 0,
    "flags": []
  },
  "msentries": [
    {
      "meendurance": 20,
      "mskill": 10,
      "mscore": 0.2681605364426094,
      "mratio": {
        "radix": 16,
        "value": "14dc0e0551665b3ecdae11fa4b0e2ac29cff35080bfd9fd559/4dc9a61d998642bbb1e62afa4fc47597b9fcd0000000000000"
      },
      "states": 18869056
    }
  ]
}