{
  "mbook": "Book03",
  "msdisciplines": [
    "Hunting",
    "Tracking",
    "Healing",
    {
      "WeaponSkill": "Sword"
    },
    "MindBlast",
    "AnimalKinship",
    "MindOverMatter"
  ],
  "variable": {
    "items": {
      "Sommerswerd": 1,
      "BodyArmor": 1,
      "Meal": 2
    },
    "gold": 15,
    "flags": [
      "Knowledge01"
    ]
  },
  "msentries": [
    {
      "meendurance": 20,
      "mskill": 10,
      "mscore": 0.7559172833772942,
      "mratio": {
        "radix": 16,
        "value": "4234406c5fa92349c9b3ff4a1f048cacb26d76d/5794c6828721caeb4b385895bfa080000000000"
      },
      "states": 26137909
    }
  ]
}