{
  "mbook": "Book05",
  "msdisciplines": [
    {
      "WeaponSkill": "Sword"
    },
    "MindOverMatter",
    "MindShield",
    "Hunting",
    "Healing",
    "MindBlast",
    "AnimalKinship",
    "SixthSense",
    "Tracking"
  ],
  "variable": {
    "items": [
      [
        "Laumspur",
        1
      ],
      [
        "Meal",
        2
      ],
      [
        "Shield",
        1
      ],
      [
        "Helmet",
        1
      ],
      [
        "StrengthPotion4",
        1
      ],
      [
        {
          "Weapon": "Sword"
        },
        1
      ]
    ],
    "gold": 15,
    "flags": [
      "HelmetIsSilver",
      "FoughtElix"
    ]
  },
  "msentries": [
    {
      "meendurance": 20,
      "mskill": 10,
      "mscore": 0.7357795465026957,
      "mratio": {
        "radix": 16,
        "value": "61612e4326ae5ab1dd2d5/84595161401484a000000"
      },
      "states": 88794090
    }
  ]
}