{"_msentries":[{"_states":21964213,"_mskill":10,"_mscore":0.3765342679938,"_mratio":{"numerator":1882671339969,"denominator":5000000000000},"_meendurance":20}],"_mbook":"Book05","_msdisciplines":[{"contents":"Sword","tag":"WeaponSkill"},{"tag":"Camouflage"},{"tag":"Hunting"},{"tag":"Healing"},{"tag":"MindOverMatter"},{"tag":"MindBlast"},{"tag":"AnimalKinship"},{"tag":"Tracking"},{"tag":"SixthSense"}],"_variable":{"_cvitems":[["Sommerswerd",1],["Shield",1],["Meal",2],["Laumspur",1],["Helmet",1]],"_cvgold":15,"_cvflags":["HelmetIsSilver"]}}